{
    "Vehicle": {
        "name": "Police",
        "asset": "helix::BP_XDrive_Veh_39",
        "doors": [
            {
                "leaveLateralOffset": -150,
                "offsetLoc": "Vector(-20, -75, 75)",
                "seatLoc": "Vector(-15, -39, 85)",
                "seatRot": "Rotator(-10, 0, 0)",
                "triggerRadius": 75
            },
            {
                "leaveLateralOffset": -150,
                "offsetLoc": "Vector(-20, 75, 75)",
                "seatLoc": "Vector(-15, 39, 85)",
                "seatRot": "Rotator(-10, 0, 0)",
                "triggerRadius": 75
            }
        ],
        "maxfuel": 20
    }
}